Metadata-Version: 2.1
Name: my-package-nizarium101
Version: 0.1.0
Summary: A useful Python package
Author: Nizar Chaouachi
Author-email: nizar.chawechy.1618@gmail.com
Classifier: Programming Language :: Python :: 3
Classifier: License :: OSI Approved :: MIT License
Classifier: Operating System :: OS Independent
Requires-Python: >=3.6
Requires-Dist: requests>=2.25.1
